{"tableName": "Число выбывших лиц по территории Республики Беларусь", "tableHeader": [["2000", "2001", "2002", "2003", "2004", "2005", "2006", "2007", "2008", "2009"]], "tableHeaderDimColumns": ["Территория Республики Беларусь", "Страны мира / Группы стран", "Уровень образования", "Потоки миграции", "Возрастной состав", "Пол", "Тип местности"], "tableRows": [[{"value": "Барановичский", "level": 2}, {"value": "Всего по странам", "level": 0}, {"value": "всего по уровням образования", "level": 0}, {"value": "Всего по всем потокам миграции", "level": 0}, {"value": "По всем возрастам", "level": 0}, {"value": "Оба пола", "level": 0}, {"value": "Всего по типам местности", "level": 0}, {"value": "1 290", "level": 0}, {"value": "1 168", "level": 0}, {"value": "1 255", "level": 0}, {"value": "1 311", "level": 0}, {"value": "1 412", "level": 0}, {"value": "1 485", "level": 0}, {"value": "1 476", "level": 0}, {"value": "1 520", "level": 0}, {"value": "1 469", "level": 0}, {"value": "1 659", "level": 0}], [{"value": "Берёзовский", "level": 2}, {"value": "Всего по странам", "level": 0}, {"value": "всего по уровням образования", "level": 0}, {"value": "Всего по всем потокам миграции", "level": 0}, {"value": "По всем возрастам", "level": 0}, {"value": "Оба пола", "level": 0}, {"value": "Всего по типам местности", "level": 0}, {"value": "1 987", "level": 0}, {"value": "1 959", "level": 0}, {"value": "1 883", "level": 0}, {"value": "2 200", "level": 0}, {"value": "2 213", "level": 0}, {"value": "2 151", "level": 0}, {"value": "2 392", "level": 0}, {"value": "2 143", "level": 0}, {"value": "2 120", "level": 0}, {"value": "2 659", "level": 0}], [{"value": "Брестский", "level": 2}, {"value": "Всего по странам", "level": 0}, {"value": "всего по уровням образования", "level": 0}, {"value": "Всего по всем потокам миграции", "level": 0}, {"value": "По всем возрастам", "level": 0}, {"value": "Оба пола", "level": 0}, {"value": "Всего по типам местности", "level": 0}, {"value": "1 530", "level": 0}, {"value": "1 729", "level": 0}, {"value": "1 726", "level": 0}, {"value": "1 882", "level": 0}, {"value": "1 822", "level": 0}, {"value": "1 593", "level": 0}, {"value": "1 594", "level": 0}, {"value": "1 664", "level": 0}, {"value": "1 529", "level": 0}, {"value": "1 340", "level": 0}], [{"value": "Ганцевичский", "level": 2}, {"value": "Всего по странам", "level": 0}, {"value": "всего по уровням образования", "level": 0}, {"value": "Всего по всем потокам миграции", "level": 0}, {"value": "По всем возрастам", "level": 0}, {"value": "Оба пола", "level": 0}, {"value": "Всего по типам местности", "level": 0}, {"value": "868", "level": 0}, {"value": "933", "level": 0}, {"value": "894", "level": 0}, {"value": "913", "level": 0}, {"value": "1 125", "level": 0}, {"value": "1 166", "level": 0}, {"value": "1 158", "level": 0}, {"value": "1 171", "level": 0}, {"value": "1 026", "level": 0}, {"value": "1 347", "level": 0}], [{"value": "Дрогичинский", "level": 2}, {"value": "Всего по странам", "level": 0}, {"value": "всего по уровням образования", "level": 0}, {"value": "Всего по всем потокам миграции", "level": 0}, {"value": "По всем возрастам", "level": 0}, {"value": "Оба пола", "level": 0}, {"value": "Всего по типам местности", "level": 0}, {"value": "1 105", "level": 0}, {"value": "1 236", "level": 0}, {"value": "1 139", "level": 0}, {"value": "1 271", "level": 0}, {"value": "1 434", "level": 0}, {"value": "1 475", "level": 0}, {"value": "1 555", "level": 0}, {"value": "1 607", "level": 0}, {"value": "1 423", "level": 0}, {"value": "1 764", "level": 0}], [{"value": "Жабинковский", "level": 2}, {"value": "Всего по странам", "level": 0}, {"value": "всего по уровням образования", "level": 0}, {"value": "Всего по всем потокам миграции", "level": 0}, {"value": "По всем возрастам", "level": 0}, {"value": "Оба пола", "level": 0}, {"value": "Всего по типам местности", "level": 0}, {"value": "642", "level": 0}, {"value": "637", "level": 0}, {"value": "583", "level": 0}, {"value": "633", "level": 0}, {"value": "686", "level": 0}, {"value": "699", "level": 0}, {"value": "768", "level": 0}, {"value": "723", "level": 0}, {"value": "694", "level": 0}, {"value": "893", "level": 0}], [{"value": "Ивановский", "level": 2}, {"value": "Всего по странам", "level": 0}, {"value": "всего по уровням образования", "level": 0}, {"value": "Всего по всем потокам миграции", "level": 0}, {"value": "По всем возрастам", "level": 0}, {"value": "Оба пола", "level": 0}, {"value": "Всего по типам местности", "level": 0}, {"value": "1 236", "level": 0}, {"value": "1 235", "level": 0}, {"value": "1 249", "level": 0}, {"value": "1 204", "level": 0}, {"value": "1 254", "level": 0}, {"value": "1 450", "level": 0}, {"value": "1 416", "level": 0}, {"value": "1 490", "level": 0}, {"value": "1 400", "level": 0}, {"value": "1 757", "level": 0}], [{"value": "Ивацевичский", "level": 2}, {"value": "Всего по странам", "level": 0}, {"value": "всего по уровням образования", "level": 0}, {"value": "Всего по всем потокам миграции", "level": 0}, {"value": "По всем возрастам", "level": 0}, {"value": "Оба пола", "level": 0}, {"value": "Всего по типам местности", "level": 0}, {"value": "1 725", "level": 0}, {"value": "1 673", "level": 0}, {"value": "1 770", "level": 0}, {"value": "1 913", "level": 0}, {"value": "1 928", "level": 0}, {"value": "1 909", "level": 0}, {"value": "2 164", "level": 0}, {"value": "2 044", "level": 0}, {"value": "2 050", "level": 0}, {"value": "2 539", "level": 0}], [{"value": "Каменецкий", "level": 2}, {"value": "Всего по странам", "level": 0}, {"value": "всего по уровням образования", "level": 0}, {"value": "Всего по всем потокам миграции", "level": 0}, {"value": "По всем возрастам", "level": 0}, {"value": "Оба пола", "level": 0}, {"value": "Всего по типам местности", "level": 0}, {"value": "1 052", "level": 0}, {"value": "1 181", "level": 0}, {"value": "1 134", "level": 0}, {"value": "1 242", "level": 0}, {"value": "1 206", "level": 0}, {"value": "1 157", "level": 0}, {"value": "1 207", "level": 0}, {"value": "1 244", "level": 0}, {"value": "1 200", "level": 0}, {"value": "1 341", "level": 0}], [{"value": "Кобринский", "level": 2}, {"value": "Всего по странам", "level": 0}, {"value": "всего по уровням образования", "level": 0}, {"value": "Всего по всем потокам миграции", "level": 0}, {"value": "По всем возрастам", "level": 0}, {"value": "Оба пола", "level": 0}, {"value": "Всего по типам местности", "level": 0}, {"value": "2 050", "level": 0}, {"value": "2 216", "level": 0}, {"value": "2 350", "level": 0}, {"value": "2 892", "level": 0}, {"value": "2 736", "level": 0}, {"value": "2 708", "level": 0}, {"value": "2 766", "level": 0}, {"value": "2 781", "level": 0}, {"value": "2 648", "level": 0}, {"value": "3 079", "level": 0}], [{"value": "Лунинецкий", "level": 2}, {"value": "Всего по странам", "level": 0}, {"value": "всего по уровням образования", "level": 0}, {"value": "Всего по всем потокам миграции", "level": 0}, {"value": "По всем возрастам", "level": 0}, {"value": "Оба пола", "level": 0}, {"value": "Всего по типам местности", "level": 0}, {"value": "1 679", "level": 0}, {"value": "1 798", "level": 0}, {"value": "1 800", "level": 0}, {"value": "1 847", "level": 0}, {"value": "1 977", "level": 0}, {"value": "2 221", "level": 0}, {"value": "2 362", "level": 0}, {"value": "2 304", "level": 0}, {"value": "2 100", "level": 0}, {"value": "2 358", "level": 0}], [{"value": "Ляховичский", "level": 2}, {"value": "Всего по странам", "level": 0}, {"value": "всего по уровням образования", "level": 0}, {"value": "Всего по всем потокам миграции", "level": 0}, {"value": "По всем возрастам", "level": 0}, {"value": "Оба пола", "level": 0}, {"value": "Всего по типам местности", "level": 0}, {"value": "955", "level": 0}, {"value": "953", "level": 0}, {"value": "1 009", "level": 0}, {"value": "1 080", "level": 0}, {"value": "1 105", "level": 0}, {"value": "1 163", "level": 0}, {"value": "1 163", "level": 0}, {"value": "1 182", "level": 0}, {"value": "1 196", "level": 0}, {"value": "1 280", "level": 0}], [{"value": "Малоритский", "level": 2}, {"value": "Всего по странам", "level": 0}, {"value": "всего по уровням образования", "level": 0}, {"value": "Всего по всем потокам миграции", "level": 0}, {"value": "По всем возрастам", "level": 0}, {"value": "Оба пола", "level": 0}, {"value": "Всего по типам местности", "level": 0}, {"value": "458", "level": 0}, {"value": "542", "level": 0}, {"value": "535", "level": 0}, {"value": "600", "level": 0}, {"value": "609", "level": 0}, {"value": "648", "level": 0}, {"value": "671", "level": 0}, {"value": "711", "level": 0}, {"value": "560", "level": 0}, {"value": "914", "level": 0}], [{"value": "Пинский", "level": 2}, {"value": "Всего по странам", "level": 0}, {"value": "всего по уровням образования", "level": 0}, {"value": "Всего по всем потокам миграции", "level": 0}, {"value": "По всем возрастам", "level": 0}, {"value": "Оба пола", "level": 0}, {"value": "Всего по типам местности", "level": 0}, {"value": "1 285", "level": 0}, {"value": "1 346", "level": 0}, {"value": "1 379", "level": 0}, {"value": "1 470", "level": 0}, {"value": "1 588", "level": 0}, {"value": "1 582", "level": 0}, {"value": "1 743", "level": 0}, {"value": "1 797", "level": 0}, {"value": "1 748", "level": 0}, {"value": "2 387", "level": 0}], [{"value": "Пружанский", "level": 2}, {"value": "Всего по странам", "level": 0}, {"value": "всего по уровням образования", "level": 0}, {"value": "Всего по всем потокам миграции", "level": 0}, {"value": "По всем возрастам", "level": 0}, {"value": "Оба пола", "level": 0}, {"value": "Всего по типам местности", "level": 0}, {"value": "1 392", "level": 0}, {"value": "1 418", "level": 0}, {"value": "1 524", "level": 0}, {"value": "1 516", "level": 0}, {"value": "1 543", "level": 0}, {"value": "1 521", "level": 0}, {"value": "1 549", "level": 0}, {"value": "1 686", "level": 0}, {"value": "1 545", "level": 0}, {"value": "1 873", "level": 0}], [{"value": "Столинский", "level": 2}, {"value": "Всего по странам", "level": 0}, {"value": "всего по уровням образования", "level": 0}, {"value": "Всего по всем потокам миграции", "level": 0}, {"value": "По всем возрастам", "level": 0}, {"value": "Оба пола", "level": 0}, {"value": "Всего по типам местности", "level": 0}, {"value": "1 854", "level": 0}, {"value": "1 921", "level": 0}, {"value": "2 004", "level": 0}, {"value": "2 017", "level": 0}, {"value": "2 151", "level": 0}, {"value": "2 217", "level": 0}, {"value": "2 341", "level": 0}, {"value": "2 199", "level": 0}, {"value": "1 853", "level": 0}, {"value": "2 429", "level": 0}], [{"value": "г. Брест", "level": 2}, {"value": "Всего по странам", "level": 0}, {"value": "всего по уровням образования", "level": 0}, {"value": "Всего по всем потокам миграции", "level": 0}, {"value": "По всем возрастам", "level": 0}, {"value": "Оба пола", "level": 0}, {"value": "Всего по типам местности", "level": 0}, {"value": "4 041", "level": 0}, {"value": "4 208", "level": 0}, {"value": "4 354", "level": 0}, {"value": "4 797", "level": 0}, {"value": "5 105", "level": 0}, {"value": "5 158", "level": 0}, {"value": "5 285", "level": 0}, {"value": "4 975", "level": 0}, {"value": "4 884", "level": 0}, {"value": "4 837", "level": 0}], [{"value": "г. Барановичи", "level": 2}, {"value": "Всего по странам", "level": 0}, {"value": "всего по уровням образования", "level": 0}, {"value": "Всего по всем потокам миграции", "level": 0}, {"value": "По всем возрастам", "level": 0}, {"value": "Оба пола", "level": 0}, {"value": "Всего по типам местности", "level": 0}, {"value": "2 909", "level": 0}, {"value": "3 093", "level": 0}, {"value": "2 978", "level": 0}, {"value": "3 320", "level": 0}, {"value": "3 407", "level": 0}, {"value": "3 569", "level": 0}, {"value": "3 480", "level": 0}, {"value": "3 701", "level": 0}, {"value": "3 995", "level": 0}, {"value": "4 286", "level": 0}], [{"value": "г. Пинск", "level": 2}, {"value": "Всего по странам", "level": 0}, {"value": "всего по уровням образования", "level": 0}, {"value": "Всего по всем потокам миграции", "level": 0}, {"value": "По всем возрастам", "level": 0}, {"value": "Оба пола", "level": 0}, {"value": "Всего по типам местности", "level": 0}, {"value": "2 682", "level": 0}, {"value": "2 868", "level": 0}, {"value": "2 875", "level": 0}, {"value": "3 184", "level": 0}, {"value": "3 213", "level": 0}, {"value": "3 352", "level": 0}, {"value": "3 308", "level": 0}, {"value": "3 117", "level": 0}, {"value": "3 343", "level": 0}, {"value": "3 734", "level": 0}], [{"value": "Бешенковичский", "level": 2}, {"value": "Всего по странам", "level": 0}, {"value": "всего по уровням образования", "level": 0}, {"value": "Всего по всем потокам миграции", "level": 0}, {"value": "По всем возрастам", "level": 0}, {"value": "Оба пола", "level": 0}, {"value": "Всего по типам местности", "level": 0}, {"value": "610", "level": 0}, {"value": "686", "level": 0}, {"value": "806", "level": 0}, {"value": "852", "level": 0}, {"value": "775", "level": 0}, {"value": "903", "level": 0}, {"value": "935", "level": 0}, {"value": "804", "level": 0}, {"value": "634", "level": 0}, {"value": "746", "level": 0}], [{"value": "Браславский", "level": 2}, {"value": "Всего по странам", "level": 0}, {"value": "всего по уровням образования", "level": 0}, {"value": "Всего по всем потокам миграции", "level": 0}, {"value": "По всем возрастам", "level": 0}, {"value": "Оба пола", "level": 0}, {"value": "Всего по типам местности", "level": 0}, {"value": "823", "level": 0}, {"value": "843", "level": 0}, {"value": "942", "level": 0}, {"value": "928", "level": 0}, {"value": "987", "level": 0}, {"value": "983", "level": 0}, {"value": "1 018", "level": 0}, {"value": "1 016", "level": 0}, {"value": "1 016", "level": 0}, {"value": "1 174", "level": 0}], [{"value": "Верхнедвинский", "level": 2}, {"value": "Всего по странам", "level": 0}, {"value": "всего по уровням образования", "level": 0}, {"value": "Всего по всем потокам миграции", "level": 0}, {"value": "По всем возрастам", "level": 0}, {"value": "Оба пола", "level": 0}, {"value": "Всего по типам местности", "level": 0}, {"value": "903", "level": 0}, {"value": "863", "level": 0}, {"value": "868", "level": 0}, {"value": "894", "level": 0}, {"value": "988", "level": 0}, {"value": "989", "level": 0}, {"value": "969", "level": 0}, {"value": "967", "level": 0}, {"value": "927", "level": 0}, {"value": "968", "level": 0}], [{"value": "Витебский", "level": 2}, {"value": "Всего по странам", "level": 0}, {"value": "всего по уровням образования", "level": 0}, {"value": "Всего по всем потокам миграции", "level": 0}, {"value": "По всем возрастам", "level": 0}, {"value": "Оба пола", "level": 0}, {"value": "Всего по типам местности", "level": 0}, {"value": "1 232", "level": 0}, {"value": "1 355", "level": 0}, {"value": "1 431", "level": 0}, {"value": "1 371", "level": 0}, {"value": "1 335", "level": 0}, {"value": "1 705", "level": 0}, {"value": "1 801", "level": 0}, {"value": "1 656", "level": 0}, {"value": "1 469", "level": 0}, {"value": "1 569", "level": 0}], [{"value": "Глубокский", "level": 2}, {"value": "Всего по странам", "level": 0}, {"value": "всего по уровням образования", "level": 0}, {"value": "Всего по всем потокам миграции", "level": 0}, {"value": "По всем возрастам", "level": 0}, {"value": "Оба пола", "level": 0}, {"value": "Всего по типам местности", "level": 0}, {"value": "1 213", "level": 0}, {"value": "1 357", "level": 0}, {"value": "1 322", "level": 0}, {"value": "1 358", "level": 0}, {"value": "1 508", "level": 0}, {"value": "1 424", "level": 0}, {"value": "1 450", "level": 0}, {"value": "1 501", "level": 0}, {"value": "1 309", "level": 0}, {"value": "1 679", "level": 0}], [{"value": "Городокский", "level": 2}, {"value": "Всего по странам", "level": 0}, {"value": "всего по уровням образования", "level": 0}, {"value": "Всего по всем потокам миграции", "level": 0}, {"value": "По всем возрастам", "level": 0}, {"value": "Оба пола", "level": 0}, {"value": "Всего по типам местности", "level": 0}, {"value": "1 145", "level": 0}, {"value": "1 245", "level": 0}, {"value": "1 196", "level": 0}, {"value": "1 244", "level": 0}, {"value": "1 219", "level": 0}, {"value": "1 348", "level": 0}, {"value": "1 273", "level": 0}, {"value": "1 418", "level": 0}, {"value": "1 137", "level": 0}, {"value": "1 380", "level": 0}], [{"value": "Докшицкий", "level": 2}, {"value": "Всего по странам", "level": 0}, {"value": "всего по уровням образования", "level": 0}, {"value": "Всего по всем потокам миграции", "level": 0}, {"value": "По всем возрастам", "level": 0}, {"value": "Оба пола", "level": 0}, {"value": "Всего по типам местности", "level": 0}, {"value": "921", "level": 0}, {"value": "1 016", "level": 0}, {"value": "995", "level": 0}, {"value": "1 135", "level": 0}, {"value": "1 113", "level": 0}, {"value": "1 082", "level": 0}, {"value": "1 134", "level": 0}, {"value": "1 138", "level": 0}, {"value": "961", "level": 0}, {"value": "1 175", "level": 0}], [{"value": "Дубровенский", "level": 2}, {"value": "Всего по странам", "level": 0}, {"value": "всего по уровням образования", "level": 0}, {"value": "Всего по всем потокам миграции", "level": 0}, {"value": "По всем возрастам", "level": 0}, {"value": "Оба пола", "level": 0}, {"value": "Всего по типам местности", "level": 0}, {"value": "712", "level": 0}, {"value": "758", "level": 0}, {"value": "718", "level": 0}, {"value": "754", "level": 0}, {"value": "793", "level": 0}, {"value": "810", "level": 0}, {"value": "788", "level": 0}, {"value": "753", "level": 0}, {"value": "527", "level": 0}, {"value": "632", "level": 0}], [{"value": "Лепельский", "level": 2}, {"value": "Всего по странам", "level": 0}, {"value": "всего по уровням образования", "level": 0}, {"value": "Всего по всем потокам миграции", "level": 0}, {"value": "По всем возрастам", "level": 0}, {"value": "Оба пола", "level": 0}, {"value": "Всего по типам местности", "level": 0}, {"value": "1 484", "level": 0}, {"value": "1 468", "level": 0}, {"value": "1 496", "level": 0}, {"value": "1 519", "level": 0}, {"value": "1 773", "level": 0}, {"value": "1 618", "level": 0}, {"value": "1 702", "level": 0}, {"value": "1 637", "level": 0}, {"value": "1 426", "level": 0}, {"value": "1 537", "level": 0}], [{"value": "Лиозненский", "level": 2}, {"value": "Всего по странам", "level": 0}, {"value": "всего по уровням образования", "level": 0}, {"value": "Всего по всем потокам миграции", "level": 0}, {"value": "По всем возрастам", "level": 0}, {"value": "Оба пола", "level": 0}, {"value": "Всего по типам местности", "level": 0}, {"value": "562", "level": 0}, {"value": "645", "level": 0}, {"value": "616", "level": 0}, {"value": "536", "level": 0}, {"value": "595", "level": 0}, {"value": "660", "level": 0}, {"value": "682", "level": 0}, {"value": "672", "level": 0}, {"value": "569", "level": 0}, {"value": "732", "level": 0}], [{"value": "Миорский", "level": 2}, {"value": "Всего по странам", "level": 0}, {"value": "всего по уровням образования", "level": 0}, {"value": "Всего по всем потокам миграции", "level": 0}, {"value": "По всем возрастам", "level": 0}, {"value": "Оба пола", "level": 0}, {"value": "Всего по типам местности", "level": 0}, {"value": "869", "level": 0}, {"value": "844", "level": 0}, {"value": "940", "level": 0}, {"value": "988", "level": 0}, {"value": "1 061", "level": 0}, {"value": "1 100", "level": 0}, {"value": "1 151", "level": 0}, {"value": "1 113", "level": 0}, {"value": "805", "level": 0}, {"value": "997", "level": 0}], [{"value": "Оршанский", "level": 2}, {"value": "Всего по странам", "level": 0}, {"value": "всего по уровням образования", "level": 0}, {"value": "Всего по всем потокам миграции", "level": 0}, {"value": "По всем возрастам", "level": 0}, {"value": "Оба пола", "level": 0}, {"value": "Всего по типам местности", "level": 0}, {"value": "4 238", "level": 0}, {"value": "4 595", "level": 0}, {"value": "4 547", "level": 0}, {"value": "4 510", "level": 0}, {"value": "4 683", "level": 0}, {"value": "4 984", "level": 0}, {"value": "4 583", "level": 0}, {"value": "4 465", "level": 0}, {"value": "3 882", "level": 0}, {"value": "4 274", "level": 0}], [{"value": "Полоцкий", "level": 2}, {"value": "Всего по странам", "level": 0}, {"value": "всего по уровням образования", "level": 0}, {"value": "Всего по всем потокам миграции", "level": 0}, {"value": "По всем возрастам", "level": 0}, {"value": "Оба пола", "level": 0}, {"value": "Всего по типам местности", "level": 0}, {"value": "3 414", "level": 0}, {"value": "3 498", "level": 0}, {"value": "3 622", "level": 0}, {"value": "3 815", "level": 0}, {"value": "3 804", "level": 0}, {"value": "3 584", "level": 0}, {"value": "3 374", "level": 0}, {"value": "3 109", "level": 0}, {"value": "3 082", "level": 0}, {"value": "3 065", "level": 0}], [{"value": "Поставский", "level": 2}, {"value": "Всего по странам", "level": 0}, {"value": "всего по уровням образования", "level": 0}, {"value": "Всего по всем потокам миграции", "level": 0}, {"value": "По всем возрастам", "level": 0}, {"value": "Оба пола", "level": 0}, {"value": "Всего по типам местности", "level": 0}, {"value": "1 265", "level": 0}, {"value": "1 321", "level": 0}, {"value": "1 276", "level": 0}, {"value": "1 385", "level": 0}, {"value": "1 420", "level": 0}, {"value": "1 600", "level": 0}, {"value": "1 534", "level": 0}, {"value": "1 453", "level": 0}, {"value": "1 243", "level": 0}, {"value": "1 655", "level": 0}], [{"value": "Россонский", "level": 2}, {"value": "Всего по странам", "level": 0}, {"value": "всего по уровням образования", "level": 0}, {"value": "Всего по всем потокам миграции", "level": 0}, {"value": "По всем возрастам", "level": 0}, {"value": "Оба пола", "level": 0}, {"value": "Всего по типам местности", "level": 0}, {"value": "330", "level": 0}, {"value": "431", "level": 0}, {"value": "381", "level": 0}, {"value": "347", "level": 0}, {"value": "408", "level": 0}, {"value": "391", "level": 0}, {"value": "400", "level": 0}, {"value": "385", "level": 0}, {"value": "360", "level": 0}, {"value": "417", "level": 0}], [{"value": "Сенненский", "level": 2}, {"value": "Всего по странам", "level": 0}, {"value": "всего по уровням образования", "level": 0}, {"value": "Всего по всем потокам миграции", "level": 0}, {"value": "По всем возрастам", "level": 0}, {"value": "Оба пола", "level": 0}, {"value": "Всего по типам местности", "level": 0}, {"value": "790", "level": 0}, {"value": "889", "level": 0}, {"value": "900", "level": 0}, {"value": "999", "level": 0}, {"value": "1 010", "level": 0}, {"value": "1 099", "level": 0}, {"value": "995", "level": 0}, {"value": "1 040", "level": 0}, {"value": "878", "level": 0}, {"value": "1 173", "level": 0}], [{"value": "Толочинский", "level": 2}, {"value": "Всего по странам", "level": 0}, {"value": "всего по уровням образования", "level": 0}, {"value": "Всего по всем потокам миграции", "level": 0}, {"value": "По всем возрастам", "level": 0}, {"value": "Оба пола", "level": 0}, {"value": "Всего по типам местности", "level": 0}, {"value": "989", "level": 0}, {"value": "1 103", "level": 0}, {"value": "1 134", "level": 0}, {"value": "1 081", "level": 0}, {"value": "1 106", "level": 0}, {"value": "1 152", "level": 0}, {"value": "1 187", "level": 0}, {"value": "1 110", "level": 0}, {"value": "856", "level": 0}, {"value": "1 055", "level": 0}], [{"value": "Ушачский", "level": 2}, {"value": "Всего по странам", "level": 0}, {"value": "всего по уровням образования", "level": 0}, {"value": "Всего по всем потокам миграции", "level": 0}, {"value": "По всем возрастам", "level": 0}, {"value": "Оба пола", "level": 0}, {"value": "Всего по типам местности", "level": 0}, {"value": "649", "level": 0}, {"value": "641", "level": 0}, {"value": "688", "level": 0}, {"value": "705", "level": 0}, {"value": "765", "level": 0}, {"value": "758", "level": 0}, {"value": "759", "level": 0}, {"value": "756", "level": 0}, {"value": "581", "level": 0}, {"value": "669", "level": 0}], [{"value": "Чашникский", "level": 2}, {"value": "Всего по странам", "level": 0}, {"value": "всего по уровням образования", "level": 0}, {"value": "Всего по всем потокам миграции", "level": 0}, {"value": "По всем возрастам", "level": 0}, {"value": "Оба пола", "level": 0}, {"value": "Всего по типам местности", "level": 0}, {"value": "1 148", "level": 0}, {"value": "1 372", "level": 0}, {"value": "1 396", "level": 0}, {"value": "1 385", "level": 0}, {"value": "1 358", "level": 0}, {"value": "1 396", "level": 0}, {"value": "1 310", "level": 0}, {"value": "1 413", "level": 0}, {"value": "1 062", "level": 0}, {"value": "1 246", "level": 0}], [{"value": "Шарковщинский", "level": 2}, {"value": "Всего по странам", "level": 0}, {"value": "всего по уровням образования", "level": 0}, {"value": "Всего по всем потокам миграции", "level": 0}, {"value": "По всем возрастам", "level": 0}, {"value": "Оба пола", "level": 0}, {"value": "Всего по типам местности", "level": 0}, {"value": "664", "level": 0}, {"value": "679", "level": 0}, {"value": "653", "level": 0}, {"value": "707", "level": 0}, {"value": "747", "level": 0}, {"value": "739", "level": 0}, {"value": "807", "level": 0}, {"value": "792", "level": 0}, {"value": "625", "level": 0}, {"value": "826", "level": 0}], [{"value": "Шумилинский", "level": 2}, {"value": "Всего по странам", "level": 0}, {"value": "всего по уровням образования", "level": 0}, {"value": "Всего по всем потокам миграции", "level": 0}, {"value": "По всем возрастам", "level": 0}, {"value": "Оба пола", "level": 0}, {"value": "Всего по типам местности", "level": 0}, {"value": "693", "level": 0}, {"value": "750", "level": 0}, {"value": "843", "level": 0}, {"value": "751", "level": 0}, {"value": "835", "level": 0}, {"value": "907", "level": 0}, {"value": "834", "level": 0}, {"value": "784", "level": 0}, {"value": "708", "level": 0}, {"value": "890", "level": 0}], [{"value": "г. Витебск", "level": 2}, {"value": "Всего по странам", "level": 0}, {"value": "всего по уровням образования", "level": 0}, {"value": "Всего по всем потокам миграции", "level": 0}, {"value": "По всем возрастам", "level": 0}, {"value": "Оба пола", "level": 0}, {"value": "Всего по типам местности", "level": 0}, {"value": "5 745", "level": 0}, {"value": "6 061", "level": 0}, {"value": "5 997", "level": 0}, {"value": "6 492", "level": 0}, {"value": "6 541", "level": 0}, {"value": "6 739", "level": 0}, {"value": "6 550", "level": 0}, {"value": "6 799", "level": 0}, {"value": "6 748", "level": 0}, {"value": "6 860", "level": 0}], [{"value": "г. Новополоцк", "level": 2}, {"value": "Всего по странам", "level": 0}, {"value": "всего по уровням образования", "level": 0}, {"value": "Всего по всем потокам миграции", "level": 0}, {"value": "По всем возрастам", "level": 0}, {"value": "Оба пола", "level": 0}, {"value": "Всего по типам местности", "level": 0}, {"value": "1 784", "level": 0}, {"value": "2 012", "level": 0}, {"value": "2 155", "level": 0}, {"value": "2 245", "level": 0}, {"value": "2 368", "level": 0}, {"value": "2 396", "level": 0}, {"value": "2 349", "level": 0}, {"value": "2 352", "level": 0}, {"value": "2 203", "level": 0}, {"value": "2 371", "level": 0}], [{"value": "Брагинский", "level": 2}, {"value": "Всего по странам", "level": 0}, {"value": "всего по уровням образования", "level": 0}, {"value": "Всего по всем потокам миграции", "level": 0}, {"value": "По всем возрастам", "level": 0}, {"value": "Оба пола", "level": 0}, {"value": "Всего по типам местности", "level": 0}, {"value": "367", "level": 0}, {"value": "375", "level": 0}, {"value": "353", "level": 0}, {"value": "371", "level": 0}, {"value": "408", "level": 0}, {"value": "377", "level": 0}, {"value": "377", "level": 0}, {"value": "361", "level": 0}, {"value": "444", "level": 0}, {"value": "483", "level": 0}], [{"value": "Буда-Кошелевский", "level": 2}, {"value": "Всего по странам", "level": 0}, {"value": "всего по уровням образования", "level": 0}, {"value": "Всего по всем потокам миграции", "level": 0}, {"value": "По всем возрастам", "level": 0}, {"value": "Оба пола", "level": 0}, {"value": "Всего по типам местности", "level": 0}, {"value": "1 183", "level": 0}, {"value": "1 333", "level": 0}, {"value": "1 256", "level": 0}, {"value": "1 271", "level": 0}, {"value": "1 291", "level": 0}, {"value": "1 519", "level": 0}, {"value": "1 622", "level": 0}, {"value": "1 372", "level": 0}, {"value": "1 325", "level": 0}, {"value": "1 473", "level": 0}], [{"value": "Ветковский", "level": 2}, {"value": "Всего по странам", "level": 0}, {"value": "всего по уровням образования", "level": 0}, {"value": "Всего по всем потокам миграции", "level": 0}, {"value": "По всем возрастам", "level": 0}, {"value": "Оба пола", "level": 0}, {"value": "Всего по типам местности", "level": 0}, {"value": "678", "level": 0}, {"value": "678", "level": 0}, {"value": "421", "level": 0}, {"value": "607", "level": 0}, {"value": "597", "level": 0}, {"value": "602", "level": 0}, {"value": "560", "level": 0}, {"value": "609", "level": 0}, {"value": "541", "level": 0}, {"value": "648", "level": 0}], [{"value": "Гомельский", "level": 2}, {"value": "Всего по странам", "level": 0}, {"value": "всего по уровням образования", "level": 0}, {"value": "Всего по всем потокам миграции", "level": 0}, {"value": "По всем возрастам", "level": 0}, {"value": "Оба пола", "level": 0}, {"value": "Всего по типам местности", "level": 0}, {"value": "1 793", "level": 0}, {"value": "1 842", "level": 0}, {"value": "1 622", "level": 0}, {"value": "1 662", "level": 0}, {"value": "1 807", "level": 0}, {"value": "1 774", "level": 0}, {"value": "1 773", "level": 0}, {"value": "1 805", "level": 0}, {"value": "2 149", "level": 0}, {"value": "2 592", "level": 0}], [{"value": "Добрушский", "level": 2}, {"value": "Всего по странам", "level": 0}, {"value": "всего по уровням образования", "level": 0}, {"value": "Всего по всем потокам миграции", "level": 0}, {"value": "По всем возрастам", "level": 0}, {"value": "Оба пола", "level": 0}, {"value": "Всего по типам местности", "level": 0}, {"value": "857", "level": 0}, {"value": "839", "level": 0}, {"value": "864", "level": 0}, {"value": "806", "level": 0}, {"value": "821", "level": 0}, {"value": "908", "level": 0}, {"value": "789", "level": 0}, {"value": "933", "level": 0}, {"value": "1 006", "level": 0}, {"value": "1 233", "level": 0}], [{"value": "Ельский", "level": 2}, {"value": "Всего по странам", "level": 0}, {"value": "всего по уровням образования", "level": 0}, {"value": "Всего по всем потокам миграции", "level": 0}, {"value": "По всем возрастам", "level": 0}, {"value": "Оба пола", "level": 0}, {"value": "Всего по типам местности", "level": 0}, {"value": "501", "level": 0}, {"value": "542", "level": 0}, {"value": "571", "level": 0}, {"value": "562", "level": 0}, {"value": "559", "level": 0}, {"value": "739", "level": 0}, {"value": "634", "level": 0}, {"value": "487", "level": 0}, {"value": "498", "level": 0}, {"value": "634", "level": 0}], [{"value": "Житковичский", "level": 2}, {"value": "Всего по странам", "level": 0}, {"value": "всего по уровням образования", "level": 0}, {"value": "Всего по всем потокам миграции", "level": 0}, {"value": "По всем возрастам", "level": 0}, {"value": "Оба пола", "level": 0}, {"value": "Всего по типам местности", "level": 0}, {"value": "1 203", "level": 0}, {"value": "1 097", "level": 0}, {"value": "1 140", "level": 0}, {"value": "1 108", "level": 0}, {"value": "1 239", "level": 0}, {"value": "1 436", "level": 0}, {"value": "1 410", "level": 0}, {"value": "1 395", "level": 0}, {"value": "1 287", "level": 0}, {"value": "1 555", "level": 0}], [{"value": "Жлобинский", "level": 2}, {"value": "Всего по странам", "level": 0}, {"value": "всего по уровням образования", "level": 0}, {"value": "Всего по всем потокам миграции", "level": 0}, {"value": "По всем возрастам", "level": 0}, {"value": "Оба пола", "level": 0}, {"value": "Всего по типам местности", "level": 0}, {"value": "1 870", "level": 0}, {"value": "1 887", "level": 0}, {"value": "1 874", "level": 0}, {"value": "2 127", "level": 0}, {"value": "1 909", "level": 0}, {"value": "1 993", "level": 0}, {"value": "1 951", "level": 0}, {"value": "2 003", "level": 0}, {"value": "1 947", "level": 0}, {"value": "2 416", "level": 0}], [{"value": "Калинковичский", "level": 2}, {"value": "Всего по странам", "level": 0}, {"value": "всего по уровням образования", "level": 0}, {"value": "Всего по всем потокам миграции", "level": 0}, {"value": "По всем возрастам", "level": 0}, {"value": "Оба пола", "level": 0}, {"value": "Всего по типам местности", "level": 0}, {"value": "1 602", "level": 0}, {"value": "1 610", "level": 0}, {"value": "1 794", "level": 0}, {"value": "1 945", "level": 0}, {"value": "1 718", "level": 0}, {"value": "2 109", "level": 0}, {"value": "1 948", "level": 0}, {"value": "2 084", "level": 0}, {"value": "1 902", "level": 0}, {"value": "2 127", "level": 0}], [{"value": "Кормянский", "level": 2}, {"value": "Всего по странам", "level": 0}, {"value": "всего по уровням образования", "level": 0}, {"value": "Всего по всем потокам миграции", "level": 0}, {"value": "По всем возрастам", "level": 0}, {"value": "Оба пола", "level": 0}, {"value": "Всего по типам местности", "level": 0}, {"value": "620", "level": 0}, {"value": "547", "level": 0}, {"value": "369", "level": 0}, {"value": "393", "level": 0}, {"value": "474", "level": 0}, {"value": "495", "level": 0}, {"value": "510", "level": 0}, {"value": "480", "level": 0}, {"value": "597", "level": 0}, {"value": "712", "level": 0}], [{"value": "Лельчицкий", "level": 2}, {"value": "Всего по странам", "level": 0}, {"value": "всего по уровням образования", "level": 0}, {"value": "Всего по всем потокам миграции", "level": 0}, {"value": "По всем возрастам", "level": 0}, {"value": "Оба пола", "level": 0}, {"value": "Всего по типам местности", "level": 0}, {"value": "640", "level": 0}, {"value": "693", "level": 0}, {"value": "722", "level": 0}, {"value": "738", "level": 0}, {"value": "682", "level": 0}, {"value": "744", "level": 0}, {"value": "674", "level": 0}, {"value": "656", "level": 0}, {"value": "666", "level": 0}, {"value": "1 148", "level": 0}], [{"value": "Лоевский", "level": 2}, {"value": "Всего по странам", "level": 0}, {"value": "всего по уровням образования", "level": 0}, {"value": "Всего по всем потокам миграции", "level": 0}, {"value": "По всем возрастам", "level": 0}, {"value": "Оба пола", "level": 0}, {"value": "Всего по типам местности", "level": 0}, {"value": "520", "level": 0}, {"value": "533", "level": 0}, {"value": "480", "level": 0}, {"value": "510", "level": 0}, {"value": "530", "level": 0}, {"value": "497", "level": 0}, {"value": "487", "level": 0}, {"value": "488", "level": 0}, {"value": "468", "level": 0}, {"value": "515", "level": 0}], [{"value": "Мозырский", "level": 2}, {"value": "Всего по странам", "level": 0}, {"value": "всего по уровням образования", "level": 0}, {"value": "Всего по всем потокам миграции", "level": 0}, {"value": "По всем возрастам", "level": 0}, {"value": "Оба пола", "level": 0}, {"value": "Всего по типам местности", "level": 0}, {"value": "2 423", "level": 0}, {"value": "2 693", "level": 0}, {"value": "2 636", "level": 0}, {"value": "2 718", "level": 0}, {"value": "2 996", "level": 0}, {"value": "3 029", "level": 0}, {"value": "2 923", "level": 0}, {"value": "2 921", "level": 0}, {"value": "3 153", "level": 0}, {"value": "3 110", "level": 0}], [{"value": "Наровлянский", "level": 2}, {"value": "Всего по странам", "level": 0}, {"value": "всего по уровням образования", "level": 0}, {"value": "Всего по всем потокам миграции", "level": 0}, {"value": "По всем возрастам", "level": 0}, {"value": "Оба пола", "level": 0}, {"value": "Всего по типам местности", "level": 0}, {"value": "398", "level": 0}, {"value": "508", "level": 0}, {"value": "462", "level": 0}, {"value": "383", "level": 0}, {"value": "285", "level": 0}, {"value": "273", "level": 0}, {"value": "317", "level": 0}, {"value": "377", "level": 0}, {"value": "334", "level": 0}, {"value": "344", "level": 0}], [{"value": "Октябрьский", "level": 2}, {"value": "Всего по странам", "level": 0}, {"value": "всего по уровням образования", "level": 0}, {"value": "Всего по всем потокам миграции", "level": 0}, {"value": "По всем возрастам", "level": 0}, {"value": "Оба пола", "level": 0}, {"value": "Всего по типам местности", "level": 0}, {"value": "590", "level": 0}, {"value": "665", "level": 0}, {"value": "615", "level": 0}, {"value": "647", "level": 0}, {"value": "653", "level": 0}, {"value": "639", "level": 0}, {"value": "585", "level": 0}, {"value": "562", "level": 0}, {"value": "534", "level": 0}, {"value": "638", "level": 0}], [{"value": "Петриковский", "level": 2}, {"value": "Всего по странам", "level": 0}, {"value": "всего по уровням образования", "level": 0}, {"value": "Всего по всем потокам миграции", "level": 0}, {"value": "По всем возрастам", "level": 0}, {"value": "Оба пола", "level": 0}, {"value": "Всего по типам местности", "level": 0}, {"value": "947", "level": 0}, {"value": "1 077", "level": 0}, {"value": "1 087", "level": 0}, {"value": "1 055", "level": 0}, {"value": "1 070", "level": 0}, {"value": "1 063", "level": 0}, {"value": "1 124", "level": 0}, {"value": "1 086", "level": 0}, {"value": "976", "level": 0}, {"value": "1 300", "level": 0}], [{"value": "Речицкий", "level": 2}, {"value": "Всего по странам", "level": 0}, {"value": "всего по уровням образования", "level": 0}, {"value": "Всего по всем потокам миграции", "level": 0}, {"value": "По всем возрастам", "level": 0}, {"value": "Оба пола", "level": 0}, {"value": "Всего по типам местности", "level": 0}, {"value": "2 979", "level": 0}, {"value": "3 173", "level": 0}, {"value": "3 112", "level": 0}, {"value": "3 166", "level": 0}, {"value": "2 898", "level": 0}, {"value": "3 173", "level": 0}, {"value": "3 100", "level": 0}, {"value": "2 987", "level": 0}, {"value": "2 905", "level": 0}, {"value": "3 314", "level": 0}], [{"value": "Рогачевский", "level": 2}, {"value": "Всего по странам", "level": 0}, {"value": "всего по уровням образования", "level": 0}, {"value": "Всего по всем потокам миграции", "level": 0}, {"value": "По всем возрастам", "level": 0}, {"value": "Оба пола", "level": 0}, {"value": "Всего по типам местности", "level": 0}, {"value": "1 949", "level": 0}, {"value": "2 086", "level": 0}, {"value": "2 113", "level": 0}, {"value": "2 060", "level": 0}, {"value": "2 231", "level": 0}, {"value": "2 228", "level": 0}, {"value": "2 061", "level": 0}, {"value": "2 081", "level": 0}, {"value": "2 002", "level": 0}, {"value": "2 343", "level": 0}], [{"value": "Светлогорский", "level": 2}, {"value": "Всего по странам", "level": 0}, {"value": "всего по уровням образования", "level": 0}, {"value": "Всего по всем потокам миграции", "level": 0}, {"value": "По всем возрастам", "level": 0}, {"value": "Оба пола", "level": 0}, {"value": "Всего по типам местности", "level": 0}, {"value": "2 165", "level": 0}, {"value": "1 979", "level": 0}, {"value": "2 006", "level": 0}, {"value": "1 745", "level": 0}, {"value": "1 921", "level": 0}, {"value": "1 890", "level": 0}, {"value": "1 838", "level": 0}, {"value": "1 895", "level": 0}, {"value": "2 022", "level": 0}, {"value": "2 560", "level": 0}], [{"value": "Хойникский", "level": 2}, {"value": "Всего по странам", "level": 0}, {"value": "всего по уровням образования", "level": 0}, {"value": "Всего по всем потокам миграции", "level": 0}, {"value": "По всем возрастам", "level": 0}, {"value": "Оба пола", "level": 0}, {"value": "Всего по типам местности", "level": 0}, {"value": "537", "level": 0}, {"value": "657", "level": 0}, {"value": "557", "level": 0}, {"value": "636", "level": 0}, {"value": "576", "level": 0}, {"value": "597", "level": 0}, {"value": "588", "level": 0}, {"value": "665", "level": 0}, {"value": "638", "level": 0}, {"value": "674", "level": 0}], [{"value": "Чечерский", "level": 2}, {"value": "Всего по странам", "level": 0}, {"value": "всего по уровням образования", "level": 0}, {"value": "Всего по всем потокам миграции", "level": 0}, {"value": "По всем возрастам", "level": 0}, {"value": "Оба пола", "level": 0}, {"value": "Всего по типам местности", "level": 0}, {"value": "561", "level": 0}, {"value": "485", "level": 0}, {"value": "415", "level": 0}, {"value": "471", "level": 0}, {"value": "474", "level": 0}, {"value": "446", "level": 0}, {"value": "465", "level": 0}, {"value": "484", "level": 0}, {"value": "462", "level": 0}, {"value": "482", "level": 0}], [{"value": "г. Гомель", "level": 2}, {"value": "Всего по странам", "level": 0}, {"value": "всего по уровням образования", "level": 0}, {"value": "Всего по всем потокам миграции", "level": 0}, {"value": "По всем возрастам", "level": 0}, {"value": "Оба пола", "level": 0}, {"value": "Всего по типам местности", "level": 0}, {"value": "6 748", "level": 0}, {"value": "7 383", "level": 0}, {"value": "7 972", "level": 0}, {"value": "8 306", "level": 0}, {"value": "8 206", "level": 0}, {"value": "8 824", "level": 0}, {"value": "8 461", "level": 0}, {"value": "8 042", "level": 0}, {"value": "8 609", "level": 0}, {"value": "7 641", "level": 0}], [{"value": "Берестовицкий", "level": 2}, {"value": "Всего по странам", "level": 0}, {"value": "всего по уровням образования", "level": 0}, {"value": "Всего по всем потокам миграции", "level": 0}, {"value": "По всем возрастам", "level": 0}, {"value": "Оба пола", "level": 0}, {"value": "Всего по типам местности", "level": 0}, {"value": "612", "level": 0}, {"value": "704", "level": 0}, {"value": "730", "level": 0}, {"value": "670", "level": 0}, {"value": "781", "level": 0}, {"value": "709", "level": 0}, {"value": "727", "level": 0}, {"value": "736", "level": 0}, {"value": "691", "level": 0}, {"value": "936", "level": 0}], [{"value": "Волковысский", "level": 2}, {"value": "Всего по странам", "level": 0}, {"value": "всего по уровням образования", "level": 0}, {"value": "Всего по всем потокам миграции", "level": 0}, {"value": "По всем возрастам", "level": 0}, {"value": "Оба пола", "level": 0}, {"value": "Всего по типам местности", "level": 0}, {"value": "1 866", "level": 0}, {"value": "1 843", "level": 0}, {"value": "1 965", "level": 0}, {"value": "2 094", "level": 0}, {"value": "2 124", "level": 0}, {"value": "2 288", "level": 0}, {"value": "2 459", "level": 0}, {"value": "2 411", "level": 0}, {"value": "2 230", "level": 0}, {"value": "3 075", "level": 0}], [{"value": "Вороновский", "level": 2}, {"value": "Всего по странам", "level": 0}, {"value": "всего по уровням образования", "level": 0}, {"value": "Всего по всем потокам миграции", "level": 0}, {"value": "По всем возрастам", "level": 0}, {"value": "Оба пола", "level": 0}, {"value": "Всего по типам местности", "level": 0}, {"value": "521", "level": 0}, {"value": "592", "level": 0}, {"value": "610", "level": 0}, {"value": "584", "level": 0}, {"value": "539", "level": 0}, {"value": "596", "level": 0}, {"value": "598", "level": 0}, {"value": "627", "level": 0}, {"value": "676", "level": 0}, {"value": "1 171", "level": 0}], [{"value": "Гродненский", "level": 2}, {"value": "Всего по странам", "level": 0}, {"value": "всего по уровням образования", "level": 0}, {"value": "Всего по всем потокам миграции", "level": 0}, {"value": "По всем возрастам", "level": 0}, {"value": "Оба пола", "level": 0}, {"value": "Всего по типам местности", "level": 0}, {"value": "1 679", "level": 0}, {"value": "1 680", "level": 0}, {"value": "1 712", "level": 0}, {"value": "1 759", "level": 0}, {"value": "1 733", "level": 0}, {"value": "1 660", "level": 0}, {"value": "1 737", "level": 0}, {"value": "1 656", "level": 0}, {"value": "1 760", "level": 0}, {"value": "2 195", "level": 0}], [{"value": "Дятловский", "level": 2}, {"value": "Всего по странам", "level": 0}, {"value": "всего по уровням образования", "level": 0}, {"value": "Всего по всем потокам миграции", "level": 0}, {"value": "По всем возрастам", "level": 0}, {"value": "Оба пола", "level": 0}, {"value": "Всего по типам местности", "level": 0}, {"value": "1 053", "level": 0}, {"value": "1 124", "level": 0}, {"value": "1 155", "level": 0}, {"value": "1 161", "level": 0}, {"value": "1 144", "level": 0}, {"value": "1 155", "level": 0}, {"value": "1 145", "level": 0}, {"value": "1 188", "level": 0}, {"value": "1 113", "level": 0}, {"value": "1 498", "level": 0}], [{"value": "Зельвенский", "level": 2}, {"value": "Всего по странам", "level": 0}, {"value": "всего по уровням образования", "level": 0}, {"value": "Всего по всем потокам миграции", "level": 0}, {"value": "По всем возрастам", "level": 0}, {"value": "Оба пола", "level": 0}, {"value": "Всего по типам местности", "level": 0}, {"value": "715", "level": 0}, {"value": "745", "level": 0}, {"value": "769", "level": 0}, {"value": "860", "level": 0}, {"value": "828", "level": 0}, {"value": "836", "level": 0}, {"value": "844", "level": 0}, {"value": "838", "level": 0}, {"value": "881", "level": 0}, {"value": "1 027", "level": 0}], [{"value": "Ивьевский", "level": 2}, {"value": "Всего по странам", "level": 0}, {"value": "всего по уровням образования", "level": 0}, {"value": "Всего по всем потокам миграции", "level": 0}, {"value": "По всем возрастам", "level": 0}, {"value": "Оба пола", "level": 0}, {"value": "Всего по типам местности", "level": 0}, {"value": "659", "level": 0}, {"value": "714", "level": 0}, {"value": "720", "level": 0}, {"value": "730", "level": 0}, {"value": "870", "level": 0}, {"value": "950", "level": 0}, {"value": "942", "level": 0}, {"value": "922", "level": 0}, {"value": "806", "level": 0}, {"value": "1 036", "level": 0}], [{"value": "Кореличский", "level": 2}, {"value": "Всего по странам", "level": 0}, {"value": "всего по уровням образования", "level": 0}, {"value": "Всего по всем потокам миграции", "level": 0}, {"value": "По всем возрастам", "level": 0}, {"value": "Оба пола", "level": 0}, {"value": "Всего по типам местности", "level": 0}, {"value": "916", "level": 0}, {"value": "937", "level": 0}, {"value": "923", "level": 0}, {"value": "952", "level": 0}, {"value": "967", "level": 0}, {"value": "939", "level": 0}, {"value": "883", "level": 0}, {"value": "877", "level": 0}, {"value": "766", "level": 0}, {"value": "1 014", "level": 0}], [{"value": "Лидский", "level": 2}, {"value": "Всего по странам", "level": 0}, {"value": "всего по уровням образования", "level": 0}, {"value": "Всего по всем потокам миграции", "level": 0}, {"value": "По всем возрастам", "level": 0}, {"value": "Оба пола", "level": 0}, {"value": "Всего по типам местности", "level": 0}, {"value": "2 502", "level": 0}, {"value": "2 392", "level": 0}, {"value": "2 562", "level": 0}, {"value": "2 689", "level": 0}, {"value": "2 668", "level": 0}, {"value": "2 995", "level": 0}, {"value": "2 831", "level": 0}, {"value": "2 892", "level": 0}, {"value": "2 760", "level": 0}, {"value": "3 732", "level": 0}], [{"value": "Мостовский", "level": 2}, {"value": "Всего по странам", "level": 0}, {"value": "всего по уровням образования", "level": 0}, {"value": "Всего по всем потокам миграции", "level": 0}, {"value": "По всем возрастам", "level": 0}, {"value": "Оба пола", "level": 0}, {"value": "Всего по типам местности", "level": 0}, {"value": "913", "level": 0}, {"value": "959", "level": 0}, {"value": "1 085", "level": 0}, {"value": "1 133", "level": 0}, {"value": "1 031", "level": 0}, {"value": "1 149", "level": 0}, {"value": "1 059", "level": 0}, {"value": "1 138", "level": 0}, {"value": "1 061", "level": 0}, {"value": "1 441", "level": 0}], [{"value": "Новогрудский", "level": 2}, {"value": "Всего по странам", "level": 0}, {"value": "всего по уровням образования", "level": 0}, {"value": "Всего по всем потокам миграции", "level": 0}, {"value": "По всем возрастам", "level": 0}, {"value": "Оба пола", "level": 0}, {"value": "Всего по типам местности", "level": 0}, {"value": "1 406", "level": 0}, {"value": "1 470", "level": 0}, {"value": "1 710", "level": 0}, {"value": "1 661", "level": 0}, {"value": "1 650", "level": 0}, {"value": "1 739", "level": 0}, {"value": "1 648", "level": 0}, {"value": "1 611", "level": 0}, {"value": "1 391", "level": 0}, {"value": "1 715", "level": 0}], [{"value": "Островецкий", "level": 2}, {"value": "Всего по странам", "level": 0}, {"value": "всего по уровням образования", "level": 0}, {"value": "Всего по всем потокам миграции", "level": 0}, {"value": "По всем возрастам", "level": 0}, {"value": "Оба пола", "level": 0}, {"value": "Всего по типам местности", "level": 0}, {"value": "568", "level": 0}, {"value": "608", "level": 0}, {"value": "549", "level": 0}, {"value": "666", "level": 0}, {"value": "679", "level": 0}, {"value": "776", "level": 0}, {"value": "735", "level": 0}, {"value": "746", "level": 0}, {"value": "614", "level": 0}, {"value": "834", "level": 0}], [{"value": "Ошмянский", "level": 2}, {"value": "Всего по странам", "level": 0}, {"value": "всего по уровням образования", "level": 0}, {"value": "Всего по всем потокам миграции", "level": 0}, {"value": "По всем возрастам", "level": 0}, {"value": "Оба пола", "level": 0}, {"value": "Всего по типам местности", "level": 0}, {"value": "974", "level": 0}, {"value": "908", "level": 0}, {"value": "1 092", "level": 0}, {"value": "993", "level": 0}, {"value": "924", "level": 0}, {"value": "940", "level": 0}, {"value": "897", "level": 0}, {"value": "772", "level": 0}, {"value": "1 055", "level": 0}, {"value": "1 258", "level": 0}], [{"value": "Свислочский", "level": 2}, {"value": "Всего по странам", "level": 0}, {"value": "всего по уровням образования", "level": 0}, {"value": "Всего по всем потокам миграции", "level": 0}, {"value": "По всем возрастам", "level": 0}, {"value": "Оба пола", "level": 0}, {"value": "Всего по типам местности", "level": 0}, {"value": "720", "level": 0}, {"value": "786", "level": 0}, {"value": "783", "level": 0}, {"value": "742", "level": 0}, {"value": "753", "level": 0}, {"value": "843", "level": 0}, {"value": "785", "level": 0}, {"value": "826", "level": 0}, {"value": "748", "level": 0}, {"value": "1 110", "level": 0}], [{"value": "Слонимский", "level": 2}, {"value": "Всего по странам", "level": 0}, {"value": "всего по уровням образования", "level": 0}, {"value": "Всего по всем потокам миграции", "level": 0}, {"value": "По всем возрастам", "level": 0}, {"value": "Оба пола", "level": 0}, {"value": "Всего по типам местности", "level": 0}, {"value": "1 932", "level": 0}, {"value": "1 872", "level": 0}, {"value": "1 801", "level": 0}, {"value": "2 018", "level": 0}, {"value": "1 900", "level": 0}, {"value": "2 089", "level": 0}, {"value": "1 958", "level": 0}, {"value": "2 087", "level": 0}, {"value": "2 038", "level": 0}, {"value": "2 530", "level": 0}], [{"value": "Сморгонский", "level": 2}, {"value": "Всего по странам", "level": 0}, {"value": "всего по уровням образования", "level": 0}, {"value": "Всего по всем потокам миграции", "level": 0}, {"value": "По всем возрастам", "level": 0}, {"value": "Оба пола", "level": 0}, {"value": "Всего по типам местности", "level": 0}, {"value": "1 657", "level": 0}, {"value": "1 621", "level": 0}, {"value": "1 808", "level": 0}, {"value": "1 798", "level": 0}, {"value": "1 926", "level": 0}, {"value": "1 965", "level": 0}, {"value": "1 931", "level": 0}, {"value": "1 899", "level": 0}, {"value": "1 701", "level": 0}, {"value": "2 291", "level": 0}], [{"value": "Щучинский", "level": 2}, {"value": "Всего по странам", "level": 0}, {"value": "всего по уровням образования", "level": 0}, {"value": "Всего по всем потокам миграции", "level": 0}, {"value": "По всем возрастам", "level": 0}, {"value": "Оба пола", "level": 0}, {"value": "Всего по типам местности", "level": 0}, {"value": "1 497", "level": 0}, {"value": "1 612", "level": 0}, {"value": "1 582", "level": 0}, {"value": "1 697", "level": 0}, {"value": "1 632", "level": 0}, {"value": "1 654", "level": 0}, {"value": "1 582", "level": 0}, {"value": "1 671", "level": 0}, {"value": "1 716", "level": 0}, {"value": "2 220", "level": 0}], [{"value": "г. Гродно", "level": 2}, {"value": "Всего по странам", "level": 0}, {"value": "всего по уровням образования", "level": 0}, {"value": "Всего по всем потокам миграции", "level": 0}, {"value": "По всем возрастам", "level": 0}, {"value": "Оба пола", "level": 0}, {"value": "Всего по типам местности", "level": 0}, {"value": "4 288", "level": 0}, {"value": "4 635", "level": 0}, {"value": "4 788", "level": 0}, {"value": "4 999", "level": 0}, {"value": "5 304", "level": 0}, {"value": "5 303", "level": 0}, {"value": "4 968", "level": 0}, {"value": "4 742", "level": 0}, {"value": "5 523", "level": 0}, {"value": "6 000", "level": 0}], [{"value": "Березинский", "level": 2}, {"value": "Всего по странам", "level": 0}, {"value": "всего по уровням образования", "level": 0}, {"value": "Всего по всем потокам миграции", "level": 0}, {"value": "По всем возрастам", "level": 0}, {"value": "Оба пола", "level": 0}, {"value": "Всего по типам местности", "level": 0}, {"value": "833", "level": 0}, {"value": "977", "level": 0}, {"value": "967", "level": 0}, {"value": "1 018", "level": 0}, {"value": "1 185", "level": 0}, {"value": "1 118", "level": 0}, {"value": "1 114", "level": 0}, {"value": "1 083", "level": 0}, {"value": "963", "level": 0}, {"value": "991", "level": 0}], [{"value": "Борисовский", "level": 2}, {"value": "Всего по странам", "level": 0}, {"value": "всего по уровням образования", "level": 0}, {"value": "Всего по всем потокам миграции", "level": 0}, {"value": "По всем возрастам", "level": 0}, {"value": "Оба пола", "level": 0}, {"value": "Всего по типам местности", "level": 0}, {"value": "4 069", "level": 0}, {"value": "4 038", "level": 0}, {"value": "3 908", "level": 0}, {"value": "4 001", "level": 0}, {"value": "4 157", "level": 0}, {"value": "4 382", "level": 0}, {"value": "4 184", "level": 0}, {"value": "4 109", "level": 0}, {"value": "3 613", "level": 0}, {"value": "4 114", "level": 0}], [{"value": "Вилейский", "level": 2}, {"value": "Всего по странам", "level": 0}, {"value": "всего по уровням образования", "level": 0}, {"value": "Всего по всем потокам миграции", "level": 0}, {"value": "По всем возрастам", "level": 0}, {"value": "Оба пола", "level": 0}, {"value": "Всего по типам местности", "level": 0}, {"value": "1 365", "level": 0}, {"value": "1 533", "level": 0}, {"value": "1 476", "level": 0}, {"value": "1 596", "level": 0}, {"value": "1 547", "level": 0}, {"value": "1 648", "level": 0}, {"value": "1 496", "level": 0}, {"value": "1 457", "level": 0}, {"value": "1 300", "level": 0}, {"value": "1 465", "level": 0}], [{"value": "Воложинский", "level": 2}, {"value": "Всего по странам", "level": 0}, {"value": "всего по уровням образования", "level": 0}, {"value": "Всего по всем потокам миграции", "level": 0}, {"value": "По всем возрастам", "level": 0}, {"value": "Оба пола", "level": 0}, {"value": "Всего по типам местности", "level": 0}, {"value": "1 205", "level": 0}, {"value": "1 260", "level": 0}, {"value": "1 391", "level": 0}, {"value": "1 389", "level": 0}, {"value": "1 427", "level": 0}, {"value": "1 401", "level": 0}, {"value": "1 345", "level": 0}, {"value": "1 380", "level": 0}, {"value": "1 182", "level": 0}, {"value": "1 550", "level": 0}], [{"value": "Дзержинский", "level": 2}, {"value": "Всего по странам", "level": 0}, {"value": "всего по уровням образования", "level": 0}, {"value": "Всего по всем потокам миграции", "level": 0}, {"value": "По всем возрастам", "level": 0}, {"value": "Оба пола", "level": 0}, {"value": "Всего по типам местности", "level": 0}, {"value": "1 335", "level": 0}, {"value": "1 438", "level": 0}, {"value": "1 511", "level": 0}, {"value": "1 420", "level": 0}, {"value": "1 536", "level": 0}, {"value": "1 455", "level": 0}, {"value": "1 443", "level": 0}, {"value": "1 187", "level": 0}, {"value": "1 049", "level": 0}, {"value": "1 505", "level": 0}], [{"value": "Клецкий", "level": 2}, {"value": "Всего по странам", "level": 0}, {"value": "всего по уровням образования", "level": 0}, {"value": "Всего по всем потокам миграции", "level": 0}, {"value": "По всем возрастам", "level": 0}, {"value": "Оба пола", "level": 0}, {"value": "Всего по типам местности", "level": 0}, {"value": "738", "level": 0}, {"value": "788", "level": 0}, {"value": "877", "level": 0}, {"value": "981", "level": 0}, {"value": "1 030", "level": 0}, {"value": "1 053", "level": 0}, {"value": "1 011", "level": 0}, {"value": "1 032", "level": 0}, {"value": "1 013", "level": 0}, {"value": "1 286", "level": 0}], [{"value": "Копыльский", "level": 2}, {"value": "Всего по странам", "level": 0}, {"value": "всего по уровням образования", "level": 0}, {"value": "Всего по всем потокам миграции", "level": 0}, {"value": "По всем возрастам", "level": 0}, {"value": "Оба пола", "level": 0}, {"value": "Всего по типам местности", "level": 0}, {"value": "1 060", "level": 0}, {"value": "1 110", "level": 0}, {"value": "1 138", "level": 0}, {"value": "1 180", "level": 0}, {"value": "1 298", "level": 0}, {"value": "1 156", "level": 0}, {"value": "1 210", "level": 0}, {"value": "1 268", "level": 0}, {"value": "1 149", "level": 0}, {"value": "1 284", "level": 0}], [{"value": "Крупский", "level": 2}, {"value": "Всего по странам", "level": 0}, {"value": "всего по уровням образования", "level": 0}, {"value": "Всего по всем потокам миграции", "level": 0}, {"value": "По всем возрастам", "level": 0}, {"value": "Оба пола", "level": 0}, {"value": "Всего по типам местности", "level": 0}, {"value": "841", "level": 0}, {"value": "867", "level": 0}, {"value": "896", "level": 0}, {"value": "864", "level": 0}, {"value": "838", "level": 0}, {"value": "894", "level": 0}, {"value": "858", "level": 0}, {"value": "878", "level": 0}, {"value": "770", "level": 0}, {"value": "969", "level": 0}], [{"value": "Логойский", "level": 2}, {"value": "Всего по странам", "level": 0}, {"value": "всего по уровням образования", "level": 0}, {"value": "Всего по всем потокам миграции", "level": 0}, {"value": "По всем возрастам", "level": 0}, {"value": "Оба пола", "level": 0}, {"value": "Всего по типам местности", "level": 0}, {"value": "1 082", "level": 0}, {"value": "1 090", "level": 0}, {"value": "1 225", "level": 0}, {"value": "1 250", "level": 0}, {"value": "1 146", "level": 0}, {"value": "1 247", "level": 0}, {"value": "1 294", "level": 0}, {"value": "1 307", "level": 0}, {"value": "1 344", "level": 0}, {"value": "1 550", "level": 0}], [{"value": "Любанский", "level": 2}, {"value": "Всего по странам", "level": 0}, {"value": "всего по уровням образования", "level": 0}, {"value": "Всего по всем потокам миграции", "level": 0}, {"value": "По всем возрастам", "level": 0}, {"value": "Оба пола", "level": 0}, {"value": "Всего по типам местности", "level": 0}, {"value": "1 124", "level": 0}, {"value": "1 163", "level": 0}, {"value": "1 201", "level": 0}, {"value": "1 190", "level": 0}, {"value": "1 212", "level": 0}, {"value": "1 281", "level": 0}, {"value": "1 291", "level": 0}, {"value": "1 216", "level": 0}, {"value": "1 081", "level": 0}, {"value": "1 085", "level": 0}], [{"value": "Минский", "level": 2}, {"value": "Всего по странам", "level": 0}, {"value": "всего по уровням образования", "level": 0}, {"value": "Всего по всем потокам миграции", "level": 0}, {"value": "По всем возрастам", "level": 0}, {"value": "Оба пола", "level": 0}, {"value": "Всего по типам местности", "level": 0}, {"value": "3 785", "level": 0}, {"value": "3 908", "level": 0}, {"value": "4 213", "level": 0}, {"value": "4 659", "level": 0}, {"value": "5 402", "level": 0}, {"value": "6 582", "level": 0}, {"value": "7 478", "level": 0}, {"value": "9 049", "level": 0}, {"value": "10 451", "level": 0}, {"value": "7 954", "level": 0}], [{"value": "Молодечненский", "level": 2}, {"value": "Всего по странам", "level": 0}, {"value": "всего по уровням образования", "level": 0}, {"value": "Всего по всем потокам миграции", "level": 0}, {"value": "По всем возрастам", "level": 0}, {"value": "Оба пола", "level": 0}, {"value": "Всего по типам местности", "level": 0}, {"value": "3 146", "level": 0}, {"value": "3 398", "level": 0}, {"value": "3 305", "level": 0}, {"value": "3 326", "level": 0}, {"value": "3 671", "level": 0}, {"value": "3 686", "level": 0}, {"value": "3 865", "level": 0}, {"value": "3 713", "level": 0}, {"value": "3 561", "level": 0}, {"value": "4 031", "level": 0}], [{"value": "Мядельский", "level": 2}, {"value": "Всего по странам", "level": 0}, {"value": "всего по уровням образования", "level": 0}, {"value": "Всего по всем потокам миграции", "level": 0}, {"value": "По всем возрастам", "level": 0}, {"value": "Оба пола", "level": 0}, {"value": "Всего по типам местности", "level": 0}, {"value": "928", "level": 0}, {"value": "1 197", "level": 0}, {"value": "1 130", "level": 0}, {"value": "1 246", "level": 0}, {"value": "1 141", "level": 0}, {"value": "1 134", "level": 0}, {"value": "1 111", "level": 0}, {"value": "1 073", "level": 0}, {"value": "933", "level": 0}, {"value": "1 413", "level": 0}], [{"value": "Несвижский", "level": 2}, {"value": "Всего по странам", "level": 0}, {"value": "всего по уровням образования", "level": 0}, {"value": "Всего по всем потокам миграции", "level": 0}, {"value": "По всем возрастам", "level": 0}, {"value": "Оба пола", "level": 0}, {"value": "Всего по типам местности", "level": 0}, {"value": "946", "level": 0}, {"value": "993", "level": 0}, {"value": "1 095", "level": 0}, {"value": "1 084", "level": 0}, {"value": "1 159", "level": 0}, {"value": "1 134", "level": 0}, {"value": "1 171", "level": 0}, {"value": "1 168", "level": 0}, {"value": "1 189", "level": 0}, {"value": "1 526", "level": 0}], [{"value": "Пуховичский", "level": 2}, {"value": "Всего по странам", "level": 0}, {"value": "всего по уровням образования", "level": 0}, {"value": "Всего по всем потокам миграции", "level": 0}, {"value": "По всем возрастам", "level": 0}, {"value": "Оба пола", "level": 0}, {"value": "Всего по типам местности", "level": 0}, {"value": "1 830", "level": 0}, {"value": "1 837", "level": 0}, {"value": "2 067", "level": 0}, {"value": "2 199", "level": 0}, {"value": "2 258", "level": 0}, {"value": "2 364", "level": 0}, {"value": "2 331", "level": 0}, {"value": "2 139", "level": 0}, {"value": "1 890", "level": 0}, {"value": "2 135", "level": 0}], [{"value": "Слуцкий", "level": 2}, {"value": "Всего по странам", "level": 0}, {"value": "всего по уровням образования", "level": 0}, {"value": "Всего по всем потокам миграции", "level": 0}, {"value": "По всем возрастам", "level": 0}, {"value": "Оба пола", "level": 0}, {"value": "Всего по типам местности", "level": 0}, {"value": "2 356", "level": 0}, {"value": "2 492", "level": 0}, {"value": "2 567", "level": 0}, {"value": "2 709", "level": 0}, {"value": "2 792", "level": 0}, {"value": "2 774", "level": 0}, {"value": "2 668", "level": 0}, {"value": "2 723", "level": 0}, {"value": "2 576", "level": 0}, {"value": "3 082", "level": 0}], [{"value": "Смолевичский", "level": 2}, {"value": "Всего по странам", "level": 0}, {"value": "всего по уровням образования", "level": 0}, {"value": "Всего по всем потокам миграции", "level": 0}, {"value": "По всем возрастам", "level": 0}, {"value": "Оба пола", "level": 0}, {"value": "Всего по типам местности", "level": 0}, {"value": "968", "level": 0}, {"value": "1 028", "level": 0}, {"value": "1 066", "level": 0}, {"value": "1 071", "level": 0}, {"value": "1 299", "level": 0}, {"value": "1 229", "level": 0}, {"value": "1 150", "level": 0}, {"value": "1 173", "level": 0}, {"value": "1 091", "level": 0}, {"value": "1 278", "level": 0}], [{"value": "Солигорский", "level": 2}, {"value": "Всего по странам", "level": 0}, {"value": "всего по уровням образования", "level": 0}, {"value": "Всего по всем потокам миграции", "level": 0}, {"value": "По всем возрастам", "level": 0}, {"value": "Оба пола", "level": 0}, {"value": "Всего по типам местности", "level": 0}, {"value": "2 823", "level": 0}, {"value": "3 271", "level": 0}, {"value": "3 452", "level": 0}, {"value": "3 512", "level": 0}, {"value": "3 709", "level": 0}, {"value": "3 844", "level": 0}, {"value": "3 573", "level": 0}, {"value": "3 482", "level": 0}, {"value": "3 317", "level": 0}, {"value": "4 107", "level": 0}], [{"value": "Стародорожский", "level": 2}, {"value": "Всего по странам", "level": 0}, {"value": "всего по уровням образования", "level": 0}, {"value": "Всего по всем потокам миграции", "level": 0}, {"value": "По всем возрастам", "level": 0}, {"value": "Оба пола", "level": 0}, {"value": "Всего по типам местности", "level": 0}, {"value": "581", "level": 0}, {"value": "572", "level": 0}, {"value": "709", "level": 0}, {"value": "622", "level": 0}, {"value": "679", "level": 0}, {"value": "637", "level": 0}, {"value": "707", "level": 0}, {"value": "650", "level": 0}, {"value": "549", "level": 0}, {"value": "641", "level": 0}], [{"value": "Столбцовский", "level": 2}, {"value": "Всего по странам", "level": 0}, {"value": "всего по уровням образования", "level": 0}, {"value": "Всего по всем потокам миграции", "level": 0}, {"value": "По всем возрастам", "level": 0}, {"value": "Оба пола", "level": 0}, {"value": "Всего по типам местности", "level": 0}, {"value": "1 098", "level": 0}, {"value": "1 154", "level": 0}, {"value": "1 377", "level": 0}, {"value": "1 320", "level": 0}, {"value": "1 347", "level": 0}, {"value": "1 473", "level": 0}, {"value": "1 536", "level": 0}, {"value": "1 450", "level": 0}, {"value": "1 387", "level": 0}, {"value": "1 823", "level": 0}], [{"value": "Узденский", "level": 2}, {"value": "Всего по странам", "level": 0}, {"value": "всего по уровням образования", "level": 0}, {"value": "Всего по всем потокам миграции", "level": 0}, {"value": "По всем возрастам", "level": 0}, {"value": "Оба пола", "level": 0}, {"value": "Всего по типам местности", "level": 0}, {"value": "659", "level": 0}, {"value": "673", "level": 0}, {"value": "731", "level": 0}, {"value": "774", "level": 0}, {"value": "800", "level": 0}, {"value": "880", "level": 0}, {"value": "789", "level": 0}, {"value": "832", "level": 0}, {"value": "894", "level": 0}, {"value": "972", "level": 0}], [{"value": "Червенский", "level": 2}, {"value": "Всего по странам", "level": 0}, {"value": "всего по уровням образования", "level": 0}, {"value": "Всего по всем потокам миграции", "level": 0}, {"value": "По всем возрастам", "level": 0}, {"value": "Оба пола", "level": 0}, {"value": "Всего по типам местности", "level": 0}, {"value": "962", "level": 0}, {"value": "983", "level": 0}, {"value": "958", "level": 0}, {"value": "1 039", "level": 0}, {"value": "1 059", "level": 0}, {"value": "1 055", "level": 0}, {"value": "1 168", "level": 0}, {"value": "1 076", "level": 0}, {"value": "920", "level": 0}, {"value": "1 077", "level": 0}], [{"value": "г. Жодино", "level": 2}, {"value": "Всего по странам", "level": 0}, {"value": "всего по уровням образования", "level": 0}, {"value": "Всего по всем потокам миграции", "level": 0}, {"value": "По всем возрастам", "level": 0}, {"value": "Оба пола", "level": 0}, {"value": "Всего по типам местности", "level": 0}, {"value": "1 073", "level": 0}, {"value": "1 090", "level": 0}, {"value": "1 236", "level": 0}, {"value": "1 329", "level": 0}, {"value": "1 390", "level": 0}, {"value": "1 378", "level": 0}, {"value": "1 383", "level": 0}, {"value": "1 501", "level": 0}, {"value": "1 203", "level": 0}, {"value": "1 320", "level": 0}], [{"value": "Белыничский", "level": 2}, {"value": "Всего по странам", "level": 0}, {"value": "всего по уровням образования", "level": 0}, {"value": "Всего по всем потокам миграции", "level": 0}, {"value": "По всем возрастам", "level": 0}, {"value": "Оба пола", "level": 0}, {"value": "Всего по типам местности", "level": 0}, {"value": "647", "level": 0}, {"value": "659", "level": 0}, {"value": "738", "level": 0}, {"value": "670", "level": 0}, {"value": "716", "level": 0}, {"value": "707", "level": 0}, {"value": "732", "level": 0}, {"value": "667", "level": 0}, {"value": "524", "level": 0}, {"value": "538", "level": 0}], [{"value": "Бобруйский", "level": 2}, {"value": "Всего по странам", "level": 0}, {"value": "всего по уровням образования", "level": 0}, {"value": "Всего по всем потокам миграции", "level": 0}, {"value": "По всем возрастам", "level": 0}, {"value": "Оба пола", "level": 0}, {"value": "Всего по типам местности", "level": 0}, {"value": "745", "level": 0}, {"value": "818", "level": 0}, {"value": "801", "level": 0}, {"value": "875", "level": 0}, {"value": "955", "level": 0}, {"value": "922", "level": 0}, {"value": "921", "level": 0}, {"value": "812", "level": 0}, {"value": "853", "level": 0}, {"value": "943", "level": 0}], [{"value": "Быховский", "level": 2}, {"value": "Всего по странам", "level": 0}, {"value": "всего по уровням образования", "level": 0}, {"value": "Всего по всем потокам миграции", "level": 0}, {"value": "По всем возрастам", "level": 0}, {"value": "Оба пола", "level": 0}, {"value": "Всего по типам местности", "level": 0}, {"value": "994", "level": 0}, {"value": "1 000", "level": 0}, {"value": "1 032", "level": 0}, {"value": "1 048", "level": 0}, {"value": "1 113", "level": 0}, {"value": "1 227", "level": 0}, {"value": "1 137", "level": 0}, {"value": "1 092", "level": 0}, {"value": "801", "level": 0}, {"value": "951", "level": 0}], [{"value": "Глусский", "level": 2}, {"value": "Всего по странам", "level": 0}, {"value": "всего по уровням образования", "level": 0}, {"value": "Всего по всем потокам миграции", "level": 0}, {"value": "По всем возрастам", "level": 0}, {"value": "Оба пола", "level": 0}, {"value": "Всего по типам местности", "level": 0}, {"value": "683", "level": 0}, {"value": "641", "level": 0}, {"value": "682", "level": 0}, {"value": "764", "level": 0}, {"value": "733", "level": 0}, {"value": "807", "level": 0}, {"value": "783", "level": 0}, {"value": "722", "level": 0}, {"value": "509", "level": 0}, {"value": "647", "level": 0}], [{"value": "Горецкий", "level": 2}, {"value": "Всего по странам", "level": 0}, {"value": "всего по уровням образования", "level": 0}, {"value": "Всего по всем потокам миграции", "level": 0}, {"value": "По всем возрастам", "level": 0}, {"value": "Оба пола", "level": 0}, {"value": "Всего по типам местности", "level": 0}, {"value": "1 938", "level": 0}, {"value": "2 113", "level": 0}, {"value": "2 162", "level": 0}, {"value": "2 161", "level": 0}, {"value": "2 386", "level": 0}, {"value": "2 385", "level": 0}, {"value": "2 321", "level": 0}, {"value": "2 365", "level": 0}, {"value": "1 915", "level": 0}, {"value": "2 147", "level": 0}], [{"value": "Дрибинский", "level": 2}, {"value": "Всего по странам", "level": 0}, {"value": "всего по уровням образования", "level": 0}, {"value": "Всего по всем потокам миграции", "level": 0}, {"value": "По всем возрастам", "level": 0}, {"value": "Оба пола", "level": 0}, {"value": "Всего по типам местности", "level": 0}, {"value": "367", "level": 0}, {"value": "356", "level": 0}, {"value": "371", "level": 0}, {"value": "422", "level": 0}, {"value": "465", "level": 0}, {"value": "497", "level": 0}, {"value": "525", "level": 0}, {"value": "506", "level": 0}, {"value": "375", "level": 0}, {"value": "381", "level": 0}], [{"value": "Кировский", "level": 2}, {"value": "Всего по странам", "level": 0}, {"value": "всего по уровням образования", "level": 0}, {"value": "Всего по всем потокам миграции", "level": 0}, {"value": "По всем возрастам", "level": 0}, {"value": "Оба пола", "level": 0}, {"value": "Всего по типам местности", "level": 0}, {"value": "881", "level": 0}, {"value": "883", "level": 0}, {"value": "966", "level": 0}, {"value": "991", "level": 0}, {"value": "1 003", "level": 0}, {"value": "948", "level": 0}, {"value": "948", "level": 0}, {"value": "986", "level": 0}, {"value": "831", "level": 0}, {"value": "934", "level": 0}], [{"value": "Климовичский", "level": 2}, {"value": "Всего по странам", "level": 0}, {"value": "всего по уровням образования", "level": 0}, {"value": "Всего по всем потокам миграции", "level": 0}, {"value": "По всем возрастам", "level": 0}, {"value": "Оба пола", "level": 0}, {"value": "Всего по типам местности", "level": 0}, {"value": "614", "level": 0}, {"value": "657", "level": 0}, {"value": "607", "level": 0}, {"value": "605", "level": 0}, {"value": "717", "level": 0}, {"value": "725", "level": 0}, {"value": "719", "level": 0}, {"value": "761", "level": 0}, {"value": "580", "level": 0}, {"value": "600", "level": 0}], [{"value": "Кличевский", "level": 2}, {"value": "Всего по странам", "level": 0}, {"value": "всего по уровням образования", "level": 0}, {"value": "Всего по всем потокам миграции", "level": 0}, {"value": "По всем возрастам", "level": 0}, {"value": "Оба пола", "level": 0}, {"value": "Всего по типам местности", "level": 0}, {"value": "575", "level": 0}, {"value": "695", "level": 0}, {"value": "759", "level": 0}, {"value": "675", "level": 0}, {"value": "710", "level": 0}, {"value": "688", "level": 0}, {"value": "702", "level": 0}, {"value": "627", "level": 0}, {"value": "647", "level": 0}, {"value": "680", "level": 0}], [{"value": "Костюковичский", "level": 2}, {"value": "Всего по странам", "level": 0}, {"value": "всего по уровням образования", "level": 0}, {"value": "Всего по всем потокам миграции", "level": 0}, {"value": "По всем возрастам", "level": 0}, {"value": "Оба пола", "level": 0}, {"value": "Всего по типам местности", "level": 0}, {"value": "741", "level": 0}, {"value": "748", "level": 0}, {"value": "690", "level": 0}, {"value": "665", "level": 0}, {"value": "732", "level": 0}, {"value": "688", "level": 0}, {"value": "710", "level": 0}, {"value": "779", "level": 0}, {"value": "669", "level": 0}, {"value": "659", "level": 0}], [{"value": "Краснопольский", "level": 2}, {"value": "Всего по странам", "level": 0}, {"value": "всего по уровням образования", "level": 0}, {"value": "Всего по всем потокам миграции", "level": 0}, {"value": "По всем возрастам", "level": 0}, {"value": "Оба пола", "level": 0}, {"value": "Всего по типам местности", "level": 0}, {"value": "265", "level": 0}, {"value": "290", "level": 0}, {"value": "275", "level": 0}, {"value": "267", "level": 0}, {"value": "355", "level": 0}, {"value": "325", "level": 0}, {"value": "362", "level": 0}, {"value": "309", "level": 0}, {"value": "341", "level": 0}, {"value": "318", "level": 0}], [{"value": "Кричевский", "level": 2}, {"value": "Всего по странам", "level": 0}, {"value": "всего по уровням образования", "level": 0}, {"value": "Всего по всем потокам миграции", "level": 0}, {"value": "По всем возрастам", "level": 0}, {"value": "Оба пола", "level": 0}, {"value": "Всего по типам местности", "level": 0}, {"value": "801", "level": 0}, {"value": "887", "level": 0}, {"value": "1 011", "level": 0}, {"value": "970", "level": 0}, {"value": "1 113", "level": 0}, {"value": "1 162", "level": 0}, {"value": "1 122", "level": 0}, {"value": "1 087", "level": 0}, {"value": "915", "level": 0}, {"value": "912", "level": 0}], [{"value": "Круглянский", "level": 2}, {"value": "Всего по странам", "level": 0}, {"value": "всего по уровням образования", "level": 0}, {"value": "Всего по всем потокам миграции", "level": 0}, {"value": "По всем возрастам", "level": 0}, {"value": "Оба пола", "level": 0}, {"value": "Всего по типам местности", "level": 0}, {"value": "496", "level": 0}, {"value": "513", "level": 0}, {"value": "474", "level": 0}, {"value": "480", "level": 0}, {"value": "539", "level": 0}, {"value": "572", "level": 0}, {"value": "553", "level": 0}, {"value": "511", "level": 0}, {"value": "400", "level": 0}, {"value": "394", "level": 0}], [{"value": "Могилевский", "level": 2}, {"value": "Всего по странам", "level": 0}, {"value": "всего по уровням образования", "level": 0}, {"value": "Всего по всем потокам миграции", "level": 0}, {"value": "По всем возрастам", "level": 0}, {"value": "Оба пола", "level": 0}, {"value": "Всего по типам местности", "level": 0}, {"value": "1 297", "level": 0}, {"value": "1 386", "level": 0}, {"value": "1 310", "level": 0}, {"value": "1 276", "level": 0}, {"value": "1 463", "level": 0}, {"value": "1 332", "level": 0}, {"value": "1 394", "level": 0}, {"value": "1 321", "level": 0}, {"value": "1 202", "level": 0}, {"value": "1 311", "level": 0}], [{"value": "Мстиславский", "level": 2}, {"value": "Всего по странам", "level": 0}, {"value": "всего по уровням образования", "level": 0}, {"value": "Всего по всем потокам миграции", "level": 0}, {"value": "По всем возрастам", "level": 0}, {"value": "Оба пола", "level": 0}, {"value": "Всего по типам местности", "level": 0}, {"value": "840", "level": 0}, {"value": "931", "level": 0}, {"value": "972", "level": 0}, {"value": "933", "level": 0}, {"value": "1 028", "level": 0}, {"value": "946", "level": 0}, {"value": "933", "level": 0}, {"value": "963", "level": 0}, {"value": "768", "level": 0}, {"value": "729", "level": 0}], [{"value": "Осиповичский", "level": 2}, {"value": "Всего по странам", "level": 0}, {"value": "всего по уровням образования", "level": 0}, {"value": "Всего по всем потокам миграции", "level": 0}, {"value": "По всем возрастам", "level": 0}, {"value": "Оба пола", "level": 0}, {"value": "Всего по типам местности", "level": 0}, {"value": "1 434", "level": 0}, {"value": "1 508", "level": 0}, {"value": "1 639", "level": 0}, {"value": "1 715", "level": 0}, {"value": "1 815", "level": 0}, {"value": "1 757", "level": 0}, {"value": "1 701", "level": 0}, {"value": "1 765", "level": 0}, {"value": "1 404", "level": 0}, {"value": "1 546", "level": 0}], [{"value": "Славгородский", "level": 2}, {"value": "Всего по странам", "level": 0}, {"value": "всего по уровням образования", "level": 0}, {"value": "Всего по всем потокам миграции", "level": 0}, {"value": "По всем возрастам", "level": 0}, {"value": "Оба пола", "level": 0}, {"value": "Всего по типам местности", "level": 0}, {"value": "453", "level": 0}, {"value": "505", "level": 0}, {"value": "510", "level": 0}, {"value": "569", "level": 0}, {"value": "636", "level": 0}, {"value": "591", "level": 0}, {"value": "575", "level": 0}, {"value": "544", "level": 0}, {"value": "412", "level": 0}, {"value": "449", "level": 0}], [{"value": "Хотимский", "level": 2}, {"value": "Всего по странам", "level": 0}, {"value": "всего по уровням образования", "level": 0}, {"value": "Всего по всем потокам миграции", "level": 0}, {"value": "По всем возрастам", "level": 0}, {"value": "Оба пола", "level": 0}, {"value": "Всего по типам местности", "level": 0}, {"value": "357", "level": 0}, {"value": "337", "level": 0}, {"value": "398", "level": 0}, {"value": "425", "level": 0}, {"value": "463", "level": 0}, {"value": "442", "level": 0}, {"value": "429", "level": 0}, {"value": "373", "level": 0}, {"value": "333", "level": 0}, {"value": "355", "level": 0}], [{"value": "Чаусский", "level": 2}, {"value": "Всего по странам", "level": 0}, {"value": "всего по уровням образования", "level": 0}, {"value": "Всего по всем потокам миграции", "level": 0}, {"value": "По всем возрастам", "level": 0}, {"value": "Оба пола", "level": 0}, {"value": "Всего по типам местности", "level": 0}, {"value": "732", "level": 0}, {"value": "805", "level": 0}, {"value": "836", "level": 0}, {"value": "864", "level": 0}, {"value": "905", "level": 0}, {"value": "958", "level": 0}, {"value": "971", "level": 0}, {"value": "787", "level": 0}, {"value": "599", "level": 0}, {"value": "640", "level": 0}], [{"value": "Чериковский", "level": 2}, {"value": "Всего по странам", "level": 0}, {"value": "всего по уровням образования", "level": 0}, {"value": "Всего по всем потокам миграции", "level": 0}, {"value": "По всем возрастам", "level": 0}, {"value": "Оба пола", "level": 0}, {"value": "Всего по типам местности", "level": 0}, {"value": "448", "level": 0}, {"value": "557", "level": 0}, {"value": "560", "level": 0}, {"value": "611", "level": 0}, {"value": "587", "level": 0}, {"value": "703", "level": 0}, {"value": "681", "level": 0}, {"value": "600", "level": 0}, {"value": "446", "level": 0}, {"value": "488", "level": 0}], [{"value": "Шкловский", "level": 2}, {"value": "Всего по странам", "level": 0}, {"value": "всего по уровням образования", "level": 0}, {"value": "Всего по всем потокам миграции", "level": 0}, {"value": "По всем возрастам", "level": 0}, {"value": "Оба пола", "level": 0}, {"value": "Всего по типам местности", "level": 0}, {"value": "1 047", "level": 0}, {"value": "1 041", "level": 0}, {"value": "1 100", "level": 0}, {"value": "1 129", "level": 0}, {"value": "1 256", "level": 0}, {"value": "1 139", "level": 0}, {"value": "1 156", "level": 0}, {"value": "1 024", "level": 0}, {"value": "772", "level": 0}, {"value": "902", "level": 0}], [{"value": "г. Могилев", "level": 2}, {"value": "Всего по странам", "level": 0}, {"value": "всего по уровням образования", "level": 0}, {"value": "Всего по всем потокам миграции", "level": 0}, {"value": "По всем возрастам", "level": 0}, {"value": "Оба пола", "level": 0}, {"value": "Всего по типам местности", "level": 0}, {"value": "4 886", "level": 0}, {"value": "5 167", "level": 0}, {"value": "5 470", "level": 0}, {"value": "5 701", "level": 0}, {"value": "5 948", "level": 0}, {"value": "6 378", "level": 0}, {"value": "5 832", "level": 0}, {"value": "5 801", "level": 0}, {"value": "5 632", "level": 0}, {"value": "5 526", "level": 0}], [{"value": "г. Бобруйск", "level": 2}, {"value": "Всего по странам", "level": 0}, {"value": "всего по уровням образования", "level": 0}, {"value": "Всего по всем потокам миграции", "level": 0}, {"value": "По всем возрастам", "level": 0}, {"value": "Оба пола", "level": 0}, {"value": "Всего по типам местности", "level": 0}, {"value": "2 908", "level": 0}, {"value": "3 137", "level": 0}, {"value": "3 605", "level": 0}, {"value": "3 441", "level": 0}, {"value": "3 631", "level": 0}, {"value": "3 695", "level": 0}, {"value": "3 649", "level": 0}, {"value": "3 390", "level": 0}, {"value": "3 258", "level": 0}, {"value": "3 728", "level": 0}]]}